CudaVox.cp311-win_amd64.pyd
CudaVox-1.7.0.data/platlib/cudart64_12.dll
CudaVox-1.7.0.data/platlib/msvcp140-fa60a6a7cbe9d53c2fc85cc85d11e44f.dll
CudaVox-1.7.0.data/platlib/vcomp140-2f698f46d09d3704e6bcba2dfe322f1d.dll
CudaVox-1.7.0.dist-info/DELVEWHEEL
CudaVox-1.7.0.dist-info/METADATA
CudaVox-1.7.0.dist-info/RECORD
CudaVox-1.7.0.dist-info/top_level.txt
CudaVox-1.7.0.dist-info/WHEEL
