Metadata-Version: 2.1
Name: CudaVox
Version: 1.7.0
Summary: Python bindings for a C++ library to convert mesh models into Voxel images with OpenMp and CUDA
Home-page: https://github.com/bjthorpe/Cad2vox
Author: Ben Thorpe
Author-email: b.j.thorpe@swansea.ac.uk
Classifier: Programming Language :: Python :: 3
Classifier: License :: OSI Approved :: MIT License
Classifier: Operating System :: POSIX :: Linux
Requires-Python: >=3.6
Requires-Dist: numpy (>=1.18)
Requires-Dist: meshio
Requires-Dist: tifffile
Requires-Dist: pillow (>=8.3)
Requires-Dist: pandas
Requires-Dist: cmake (>=3.22.0)
Requires-Dist: pybind11
